{"errors":[],"warnings":[],"namedChunkGroups":{"app":{"chunks":[4,1,0],"assets":["webpack-runtime-584a33425870e06994bb.js","webpack-runtime-584a33425870e06994bb.js.map","commons-487d38bec414ba5177c2.js","commons-487d38bec414ba5177c2.js.map","app-e71e93478756fe3a1578.js","app-e71e93478756fe3a1578.js.map"],"children":{},"childAssets":{}},"component---app-pages-index-js":{"chunks":[3,2],"assets":["styles.c8621ba002e48a7c702e.css","styles-196ca1f690d71623c8af.js","styles-196ca1f690d71623c8af.js.map","component---app-pages-index-js-1912449dacdc0de26501.js","component---app-pages-index-js-1912449dacdc0de26501.js.map"],"children":{},"childAssets":{}}},"assetsByChunkName":{"app":["webpack-runtime-584a33425870e06994bb.js","commons-487d38bec414ba5177c2.js","app-e71e93478756fe3a1578.js"],"component---app-pages-index-js":["styles.c8621ba002e48a7c702e.css","styles-196ca1f690d71623c8af.js","component---app-pages-index-js-1912449dacdc0de26501.js"]}}